brave_siren/__init__.py
brave_siren/cli.py
brave_siren/generator.py
brave_siren-0.1.0.dist-info/METADATA
brave_siren-0.1.0.dist-info/WHEEL
brave_siren-0.1.0.dist-info/entry_points.txt
brave_siren-0.1.0.dist-info/top_level.txt
brave_siren-0.1.0.dist-info/RECORD
