Metadata-Version: 2.1
Name: brave-siren
Version: 0.1.0
Summary: A package to generate receipts from order data in JSON format.
Author: Semyon Drozdov
Author-email: Semyon Drozdov <s.drozdov@edu.centraluniversity.ru>
